lscsde_workspace_mgmt/__init__.py
lscsde_workspace_mgmt/_version.py
lscsde_workspace_mgmt/datasourcebindingclient.py
lscsde_workspace_mgmt/datasourceclient.py
lscsde_workspace_mgmt/eventclient.py
lscsde_workspace_mgmt/exceptions.py
lscsde_workspace_mgmt/k8sio.py
lscsde_workspace_mgmt/managers.py
lscsde_workspace_mgmt/models.py
lscsde_workspace_mgmt/namespacedclient.py
lscsde_workspace_mgmt/objects.py
lscsde_workspace_mgmt/pvclient.py
lscsde_workspace_mgmt/workspacebindingclient.py
lscsde_workspace_mgmt/workspaceclient.py
lscsde_workspace_mgmt/tests/datasources.py
lscsde_workspace_mgmt/tests/datasourcesbindings.py
lscsde_workspace_mgmt/tests/k8shelper.py
lscsde_workspace_mgmt/tests/workspacebindings.py
lscsde_workspace_mgmt/tests/workspaces.py
lscsde_workspace_mgmt-0.1.14.dist-info/METADATA
lscsde_workspace_mgmt-0.1.14.dist-info/WHEEL
lscsde_workspace_mgmt-0.1.14.dist-info/licenses/LICENSE
lscsde_workspace_mgmt-0.1.14.dist-info/RECORD
