Metadata-Version: 2.4
Name: lscsde_workspace_mgmt
Version: 0.1.14
Summary: LSCSDE Workspace Management
Project-URL: Homepage, https://github.com/lsc-sde/py-lscsde-workspace-mgmt
Project-URL: Issues, https://github.com/lsc-sde/py-lscsde-workspace-mgmt/issues
Author-email: Shaun Turner <shaun.turner1@nhs.net>
License-File: LICENSE
Classifier: License :: OSI Approved :: MIT License
Classifier: Operating System :: OS Independent
Classifier: Programming Language :: Python :: 3
Requires-Python: >=3.8
Requires-Dist: importlib-metadata; python_version < '3.10'
Requires-Dist: kubernetes-asyncio
Requires-Dist: pydantic
Requires-Dist: pytz
